<?xml version="1.0" encoding="utf-8" ?>
<LanguageData>

    <CallOnRadio>Chamar {0}</CallOnRadio>
    <CannotUseSolarFlare>Não pode ser usado (explosão solar)</CannotUseSolarFlare>
    <CannotUseNoPower>Não pode ser usado (sem energia)</CannotUseNoPower>
    <CannotUseNoPath>Não pode ser usado (sem caminho)</CannotUseNoPath>
    <CannotUseReserved>Não pode ser usado (reservado)</CannotUseReserved>
    <CannotUseFull>Não pode ser usado (cheio)</CannotUseFull>

    <FireAt>Atirar em {0}</FireAt>

    <OutOfRange>fora de alcance</OutOfRange>
    <CannotHitTarget>impossível acertar alvo</CannotHitTarget>
    <CannotFight>{0} não pode lutar</CannotFight>

    <OrderManThing>Homem {0}</OrderManThing>

    <MeleeAttack>Atacar corpo-a-corpo {0}</MeleeAttack>
    <MeleeAttackToDeath>Atacar corpo-a-corpo {0} até a morte</MeleeAttackToDeath>
    <NoPath>sem caminho</NoPath>

    <ForbiddenLower>proibido</ForbiddenLower>
    <SociallyImproperLower>socialmente impróprio</SociallyImproperLower>
    <PrisonerRoomLower>quarto de prisioneiro</PrisonerRoomLower>
    <BurningLower>queimando</BurningLower>
    <NoEmptyPlaceLower>sem espaço vazio configurado para armazená-lo</NoEmptyPlaceLower>
    <AlreadyFilledLower>já está cheio o bastante</AlreadyFilledLower>
    <MissingMaterials>materiais necessários</MissingMaterials>

    <CannotGoNoPath>Impossível ir aqui (sem caminho)</CannotGoNoPath>
    <GoHere>Ir aqui</GoHere>

    <Arrest>Prender {0}</Arrest>
    <CannotArrest>Impossível prender</CannotArrest>

    <Capture>Capturar {0}</Capture>
    <CannotCapture>Impossível capturar</CannotCapture>

    <Rescue>Resgatar {0}</Rescue>
    <CannotRescue>Impossível resgatar</CannotRescue>

    <CarryToCryptosleepCasket>Carregue {0} para o caixão de cryto-sono</CarryToCryptosleepCasket>
    <CannotCarryToCryptosleepCasket>Não é possivel carregar para caixão de cryto-sono</CannotCarryToCryptosleepCasket>

    <NoCryptosleepCasket>Sem caixão de cryto-sono disponível.</NoCryptosleepCasket>
    <NoPrisonerBed>Sem cama de prisioneiro disponível.</NoPrisonerBed>
    <NoNonPrisonerBed>Sem cama de prisioneiro disponível.</NoNonPrisonerBed>
    <Reserved>Reservado por outra pessoa.</Reserved>
    <ReservedBy>Reservado por {0}.</ReservedBy>
    <IsReservedBy>{0} está reservado por {1}.</IsReservedBy>

    <NoManipulationSkill>incapaz</NoManipulationSkill>

    <Equip>Equipar {0}</Equip>
    <EquipWarningBrawler>(brawler ficará infeliz)</EquipWarningBrawler>
    <CannotEquip>Impossível equipar {0}</CannotEquip>

    <Wear>Vestir {0}</Wear>
    <CannotWear>Impossível vestir {0}</CannotWear>

    <Strip>Tirar roupas de {0}</Strip>
    <CannotStrip>Impossível tirar as roupas {0}</CannotStrip>

    <Deposit>Depositar {0} em {1}</Deposit>
    <CannotDeposit>Impossível depositar {0} em {1}</CannotDeposit>

    <SelfDestructHere>Auto-destruir aqui</SelfDestructHere>

    <Drop>Largar {0}</Drop>

    <UseMedicalBed>Descansar até estar completamente curado</UseMedicalBed>
    <NotInjured>Não machucado</NotInjured>
    <SomeoneElseSleeping>Ocupado</SomeoneElseSleeping>

    <!-- Specific thing interactions -->
    <EnterCryptosleepPod>Entrar no caixão de cryto-sono</EnterCryptosleepPod>
    <OpenCryptosleepCasket>Abrir caixão de cryto-sono</OpenCryptosleepCasket>

    <!-- e.g. Cannot VERB OBJECT, Cannot repair wall, Cannot haul metal, etc.-->
    <CannotGenericWork>Não pode {0} {1}</CannotGenericWork>

    <!-- e.g. Already GERUND OBJECt, Already repairing wall, already hauling metal, etc-->
    <CannotMissingHealthActivities>Não pode priorizar (problema de saúde: {0})</CannotMissingHealthActivities>

    <CannotGenericAlreadyAm>Já está {0} {1}</CannotGenericAlreadyAm>

    <CannotPrioritizeIsNotA>Não pode priorizar ({0} não é {1})</CannotPrioritizeIsNotA>

    <CannotPrioritizeResearch>Não pode priorizar (pesquisa é uma tarefa de longo-termo)</CannotPrioritizeResearch>

    <CannotPrioritizeForbidden>Não pode priorizar ({0} é proibido)</CannotPrioritizeForbidden>

    <!-- e.g. Prioritize GERUND OBJECT, Prioritize repairing wall, prioritize hauling metal, etc-->
    <PrioritizeGeneric>Priorizar {0} {1}</PrioritizeGeneric>

</LanguageData>

<AnimalInteractedTooRecently>Add your translation here</AnimalInteractedTooRecently>
<AnimalsSkillTooLow>Add your translation here</AnimalsSkillTooLow>
<AttackFactionBase>Add your translation here</AttackFactionBase>
<CannotCarryToExit>Add your translation here</CannotCarryToExit>
<CannotGiveToPackAnimal>Add your translation here</CannotGiveToPackAnimal>
<CannotGiveToPackAnimalAll>Add your translation here</CannotGiveToPackAnimalAll>
<CannotOrderNonControlledLower>Add your translation here</CannotOrderNonControlledLower>
<CannotPickUp>Add your translation here</CannotPickUp>
<CannotPickUpAll>Add your translation here</CannotPickUpAll>
<CannotPrioritizeForbiddenOutsideAllowedArea>Add your translation here</CannotPrioritizeForbiddenOutsideAllowedArea>
<CannotPrioritizeNotAssignedToWorkType>Add your translation here</CannotPrioritizeNotAssignedToWorkType>
<CannotPrioritizeWorkTypeDisabled>Add your translation here</CannotPrioritizeWorkTypeDisabled>
<CannotTrade>Add your translation here</CannotTrade>
<CannotUseReason>Add your translation here</CannotUseReason>
<CannotWearBecauseOfMissingBodyParts>Add your translation here</CannotWearBecauseOfMissingBodyParts>
<CarryToExit>Add your translation here</CarryToExit>
<ConsumeThing>Add your translation here</ConsumeThing>
<DropAtEdge>Add your translation here</DropAtEdge>
<DropInCenter>Add your translation here</DropInCenter>
<EnterCryptosleepCasket>Add your translation here</EnterCryptosleepCasket>
<EnterMap>Add your translation here</EnterMap>
<ForbiddenOutsideAllowedAreaLower>Add your translation here</ForbiddenOutsideAllowedAreaLower>
<ForceWear>Add your translation here</ForceWear>
<GiveToPackAnimal>Add your translation here</GiveToPackAnimal>
<GiveToPackAnimalAll>Add your translation here</GiveToPackAnimalAll>
<GiveToPackAnimalCount>Add your translation here</GiveToPackAnimalCount>
<GiveToPackAnimalSome>Add your translation here</GiveToPackAnimalSome>
<Incapable>Add your translation here</Incapable>
<IncapableOfCapacity>Add your translation here</IncapableOfCapacity>
<IsIncapableOfViolenceLower>Add your translation here</IsIncapableOfViolenceLower>
<IsNotDraftedLower>Add your translation here</IsNotDraftedLower>
<LeaderUnavailable>Add your translation here</LeaderUnavailable>
<MinSkill>Add your translation here</MinSkill>
<MissingSkill>Add your translation here</MissingSkill>
<NoAnimalBed>Add your translation here</NoAnimalBed>
<NoComponentsToRepair>Add your translation here</NoComponentsToRepair>
<NoEmptyGraveLower>Add your translation here</NoEmptyGraveLower>
<NoFood>Add your translation here</NoFood>
<NoFuelToRefuel>Add your translation here</NoFuelToRefuel>
<NoUsableFood>Add your translation here</NoUsableFood>
<NoWort>Add your translation here</NoWort>
<NotInHomeArea>Add your translation here</NotInHomeArea>
<PickUp>Add your translation here</PickUp>
<PickUpAll>Add your translation here</PickUpAll>
<PickUpCount>Add your translation here</PickUpCount>
<PickUpSome>Add your translation here</PickUpSome>
<TooHeavy>Add your translation here</TooHeavy>
<TradeWith>Add your translation here</TradeWith>
<TryToArrest>Add your translation here</TryToArrest>
<VisitFactionBase>Add your translation here</VisitFactionBase>