<?xml version="1.0" encoding="UTF-8"?>
<LanguageData>
  
  <!-- EN: totemic boards -->
  <Boards_Totemic.label>tabuleiros totêmicos</Boards_Totemic.label>
  <!-- EN: Fine wood boards decorated in a totemic style. -->
  <Boards_Totemic.description>Placas de madeira nobres decoradas em estilo totêmico.</Boards_Totemic.description>
  
  <!-- EN: diamond mindbend carpet -->
  <Carpet_MindbendA.label>carpete diamante mental</Carpet_MindbendA.label>
  <!-- EN: Fine carpet decorated in a mind-bending style often associated with drug use. -->
  <Carpet_MindbendA.description>Carpete fino decorado em um estilo alucinante, frequentemente associado ao uso de drogas.</Carpet_MindbendA.description>
  
  <!-- EN: purple mindbend carpet -->
  <Carpet_MindbendB.label>carpete roxo mental</Carpet_MindbendB.label>
  <!-- EN: Fine carpet decorated in a mind-bending style often associated with drug use. -->
  <Carpet_MindbendB.description>Carpete fino decorado em um estilo alucinante, frequentemente associado ao uso de drogas.</Carpet_MindbendB.description>
  
  <!-- EN: green mindbend carpet -->
  <Carpet_MindbendC.label>carpete verde mental</Carpet_MindbendC.label>
  <!-- EN: Fine carpet decorated in a mind-bending style often associated with drug use. -->
  <Carpet_MindbendC.description>Carpete fino decorado em um estilo alucinante, frequentemente associado ao uso de drogas.</Carpet_MindbendC.description>
  
  <!-- EN: blue mindbend carpet -->
  <Carpet_MindbendD.label>carpete azul mental</Carpet_MindbendD.label>
  <!-- EN: Fine carpet decorated in a mind-bending style often associated with drug use. -->
  <Carpet_MindbendD.description>Carpete fino decorado em um estilo alucinante, frequentemente associado ao uso de drogas.</Carpet_MindbendD.description>
  
  <!-- EN: yellow mindbend carpet -->
  <Carpet_MindbendE.label>carpete amarelo mental</Carpet_MindbendE.label>
  <!-- EN: Fine carpet decorated in a mind-bending style often associated with drug use. -->
  <Carpet_MindbendE.description>Carpete fino decorado em um estilo alucinante, frequentemente associado ao uso de drogas.</Carpet_MindbendE.description>
  
  <!-- EN: spikecore plates -->
  <Plates_Spikecore.label>placas espinhosas</Plates_Spikecore.label>
  <!-- EN: Fine steel plates decorated in an aggressive spikecore style. -->
  <Plates_Spikecore.description>Placas de aço finas decoradas em um estilo agressivo de cravo.</Plates_Spikecore.description>
  
  <!-- EN: morbid granite tile -->
  <Tile_MorbidGranite.label>ladrilho de granito mórbido</Tile_MorbidGranite.label>
  <!-- EN: Fine stone tiles in a morbid style. -->
  <Tile_MorbidGranite.description>Ladrilhos de pedra fina de estilo mórbido</Tile_MorbidGranite.description>
  
  <!-- EN: morbid limestone tile -->
  <Tile_MorbidLimestone.label>ladrilho de calcário mórbido</Tile_MorbidLimestone.label>
  <!-- EN: Fine stone tiles in a morbid style. -->
  <Tile_MorbidLimestone.description>Ladrilhos de pedra fina de estilo mórbido.</Tile_MorbidLimestone.description>
  
  <!-- EN: morbid marble tile -->
  <Tile_MorbidMarble.label>ladrilho de mármore mórbido</Tile_MorbidMarble.label>
  <!-- EN: Fine stone tiles in a morbid style. -->
  <Tile_MorbidMarble.description>Ladrilhos de pedra fina de estilo mórbido.</Tile_MorbidMarble.description>
  
  <!-- EN: morbid sandstone tile -->
  <Tile_MorbidSandstone.label>ladrilho de arenito mórbido</Tile_MorbidSandstone.label>
  <!-- EN: Fine stone tiles in a morbid style. -->
  <Tile_MorbidSandstone.description>Ladrilhos de pedra fina de estilo mórbido</Tile_MorbidSandstone.description>
  
  <!-- EN: morbid slate tile -->
  <Tile_MorbidSlate.label>ladrilho de ardósia mórbido</Tile_MorbidSlate.label>
  <!-- EN: Fine stone tiles in a morbid style. -->
  <Tile_MorbidSlate.description>Ladrilhos de pedra fina de estilo mórbido.</Tile_MorbidSlate.description>
  
  <!-- EN: granite spikecore tile -->
  <Tile_SpikecoreGranite.label>ladrilho de granito espinhoso</Tile_SpikecoreGranite.label>
  <!-- EN: Fine stone tiles in a spikecore style. -->
  <Tile_SpikecoreGranite.description>Ladrilhos de pedra fina em estilo espiqueiro.</Tile_SpikecoreGranite.description>
  
  <!-- EN: limestone spikecore tile -->
  <Tile_SpikecoreLimestone.label>ladrilho de calcário espinhoso</Tile_SpikecoreLimestone.label>
  <!-- EN: Fine stone tiles in a spikecore style. -->
  <Tile_SpikecoreLimestone.description>Ladrilhos de pedra fina em estilo espiqueiro.</Tile_SpikecoreLimestone.description>
  
  <!-- EN: marble spikecore tile -->
  <Tile_SpikecoreMarble.label>ladrilho de mármore espinhoso</Tile_SpikecoreMarble.label>
  <!-- EN: Fine stone tiles in a spikecore style. -->
  <Tile_SpikecoreMarble.description>Ladrilhos de pedra fina em estilo espiqueiro.</Tile_SpikecoreMarble.description>
  
  <!-- EN: sandstone spikecore tile -->
  <Tile_SpikecoreSandstone.label>ladrilho de arenito espinhoso</Tile_SpikecoreSandstone.label>
  <!-- EN: Fine stone tiles in a spikecore style. -->
  <Tile_SpikecoreSandstone.description>Ladrilhos de pedra fina em estilo espiqueiro.</Tile_SpikecoreSandstone.description>
  
  <!-- EN: slate spikecore tile -->
  <Tile_SpikecoreSlate.label>ladrilho de ardósia com cravo</Tile_SpikecoreSlate.label>
  <!-- EN: Fine stone tiles in a spikecore style. -->
  <Tile_SpikecoreSlate.description>Ladrilhos de pedra fina em estilo espiqueiro.</Tile_SpikecoreSlate.description>
  
  <!-- EN: totemic granite tile -->
  <Tile_TotemicGranite.label>ladrilho de granito totêmico</Tile_TotemicGranite.label>
  <!-- EN: Fine stone tiles in a totemic style. -->
  <Tile_TotemicGranite.description>Ladrilhos de pedra fina em estilo totêmico.</Tile_TotemicGranite.description>
  
  <!-- EN: totemic limestone tile -->
  <Tile_TotemicLimestone.label>ladrilho de calcário totêmico</Tile_TotemicLimestone.label>
  <!-- EN: Fine stone tiles in a totemic style. -->
  <Tile_TotemicLimestone.description>Ladrilhos de pedra fina em estilo totêmico.</Tile_TotemicLimestone.description>
  
  <!-- EN: totemic marble tile -->
  <Tile_TotemicMarble.label>ladrilho de mármore totêmico</Tile_TotemicMarble.label>
  <!-- EN: Fine stone tiles in a totemic style. -->
  <Tile_TotemicMarble.description>Ladrilhos de pedra fina em estilo totêmico.</Tile_TotemicMarble.description>
  
  <!-- EN: totemic sandstone tile -->
  <Tile_TotemicSandstone.label>ladrilho de arenito totêmico</Tile_TotemicSandstone.label>
  <!-- EN: Fine stone tiles in a totemic style. -->
  <Tile_TotemicSandstone.description>Ladrilhos de pedra fina em estilo totêmico.</Tile_TotemicSandstone.description>
  
  <!-- EN: totemic slate tile -->
  <Tile_TotemicSlate.label>ladrilho de ardósia totêmico</Tile_TotemicSlate.label>
  <!-- EN: Fine stone tiles in a totemic style. -->
  <Tile_TotemicSlate.description>Ladrilhos de pedra fina em estilo totêmico.</Tile_TotemicSlate.description>
  
  <!-- EN: hex tile -->
  <Tile_Transhumanist.label>ladrilho hexagonal</Tile_Transhumanist.label>
  <!-- EN: Fine steel plates with a hexagonal pattern for that ultra-technological look. -->
  <Tile_Transhumanist.description>Placas finas de aço com padrão hexagonal para aquele visual ultra-tecnológico.</Tile_Transhumanist.description>
  
</LanguageData>