<?xml version="1.0" encoding="utf-8"?>
<LanguageData>

  <Arrow_Short.label>flecha de arco curto</Arrow_Short.label>

  <Bow_Short.label>arco curto</Bow_Short.label>
  <Bow_Short.description>Um arco curto e simples, feito com habilidade, mas usado apenas da tecnologia mais primitiva.</Bow_Short.description>

  <Pilum_Thrown.label>dardo (jogado)</Pilum_Thrown.label>

  <Pila.label>dardo</Pila.label>
  <Pila.description>Um conjunto de dardos, lanças de arremesso não reutilizáveis.</Pila.description>

  <Arrow_Great.label>flecha de arco grande</Arrow_Great.label>

  <Bow_Great.label>arco grande</Bow_Great.label>
  <Bow_Great.description>Um grande arco poderoso. Dispara uma flecha pesada a longas distâncias.</Bow_Great.description>


</LanguageData>
