<?xml version="1.0" encoding="UTF-8"?>
<LanguageData>
  
  <!-- EN: Quality factors determine the engine's cooldown duration and the chance for a mishap when landing. -->
  <GravshipLaunch.description>Fatores de qualidade determinam a duração do tempo de recarga do motor e a chance de um incidente ao pousar.</GravshipLaunch.description>
  <!-- EN: {PAWN_labelShort}'s piloting ability -->
  <GravshipLaunch.comps.0.label>Habilidade de pilotagem de {PAWN_labelShort}</GravshipLaunch.comps.0.label>
  <!-- EN: pilot's piloting ability -->
  <GravshipLaunch.comps.0.labelAbstract>Habilidade de pilotagem do piloto</GravshipLaunch.comps.0.labelAbstract>
  <!-- EN: {PAWN_labelShort}'s piloting ability -->
  <GravshipLaunch.comps.1.label>Habilidade de pilotagem de {PAWN_labelShort}</GravshipLaunch.comps.1.label>
  <!-- EN: copilot's piloting ability -->
  <GravshipLaunch.comps.1.labelAbstract>Habilidade de pilotagem do copiloto</GravshipLaunch.comps.1.labelAbstract>
  <!-- EN: crew count -->
  <GravshipLaunch.comps.2.label>Número de Tripulantes</GravshipLaunch.comps.2.label>
  <!-- EN: small thrusters -->
  <GravshipLaunch.comps.3.label>Propulsores Pequenos</GravshipLaunch.comps.3.label>
  <!-- EN: large thrusters -->
  <GravshipLaunch.comps.4.label>Propulsores Grandes</GravshipLaunch.comps.4.label>
  <!-- EN: pilot subpersona core -->
  <GravshipLaunch.comps.5.label>Núcleo de Subpersona do Piloto</GravshipLaunch.comps.5.label>
  <!-- EN: At the current quality, the gravship won't be able to launch again for {0_time} after landing. -->
  <GravshipLaunch.extraOutcomeDescriptions.0.description>No nível atual de qualidade, a gravinave não poderá ser lançada novamente por {0_time} após o pouso.</GravshipLaunch.extraOutcomeDescriptions.0.description>
  <!-- EN: Additionally, there's a {0_percentage} chance of having a minor incident when landing the gravship. -->
  <GravshipLaunch.extraOutcomeDescriptions.1.description>Além disso, há uma chance de {0_percentage} de ocorrer um incidente pequeno ao pousar a gravinave.</GravshipLaunch.extraOutcomeDescriptions.1.description>
  
</LanguageData>