<?xml version="1.0" encoding="UTF-8"?>
<LanguageData>
  
  <!-- EN: amniotic fluid -->
  <Filth_AmnioticFluid.label>flúido amniótico</Filth_AmnioticFluid.label>
  
  <!-- EN: animal filth -->
  <Filth_AnimalFilth.label>sujeira animal</Filth_AnimalFilth.label>
  
  <!-- EN: ash -->
  <Filth_Ash.label>cinza</Filth_Ash.label>
  
  <!-- EN: blast mark -->
  <Filth_BlastMark.label>TODO</Filth_BlastMark.label>
  
  <!-- EN: blood -->
  <Filth_Blood.label>sangue</Filth_Blood.label>
  
  <!-- EN: bugblood -->
  <Filth_BloodInsect.label>sangue de inseto</Filth_BloodInsect.label>
  
  <!-- EN: blood smear -->
  <Filth_BloodSmear.label>mancha de sangue</Filth_BloodSmear.label>
  
  <!-- EN: corpse bile -->
  <Filth_CorpseBile.label>líquido de cadaver podre</Filth_CorpseBile.label>
  
  <!-- EN: dirt -->
  <Filth_Dirt.label>terra</Filth_Dirt.label>
  
  <!-- EN: firefoam -->
  <Filth_FireFoam.label>espuma de supressão ao fogo</Filth_FireFoam.label>
  
  <!-- EN: chemfuel puddle -->
  <Filth_Fuel.label>poça de combustível químico</Filth_Fuel.label>
  <!-- EN: A puddle of flammable chemfuel. -->
  <Filth_Fuel.description>uma poça de combustível químico inflamável</Filth_Fuel.description>
  
  <!-- EN: gestation fluid -->
  <Filth_GestationFluid.label>TODO</Filth_GestationFluid.label>
  
  <!-- EN: hair -->
  <Filth_Hair.label>cabelo</Filth_Hair.label>
  
  <!-- EN: loose ground -->
  <Filth_LooseGround.label>terra solta</Filth_LooseGround.label>
  
  <!-- EN: machine bits -->
  <Filth_MachineBits.label>bits de máquina</Filth_MachineBits.label>
  
  <!-- EN: ragged uniform -->
  <Filth_MoldyUniform.label>uniforme esfarrapado</Filth_MoldyUniform.label>
  
  <!-- EN: oil smear -->
  <Filth_OilSmear.label>esfregaço de óleo</Filth_OilSmear.label>
  
  <!-- EN: building rubble -->
  <Filth_RubbleBuilding.label>entulho de construção</Filth_RubbleBuilding.label>
  
  <!-- EN: rock rubble -->
  <Filth_RubbleRock.label>entulho de rocha</Filth_RubbleRock.label>
  
  <!-- EN: sand -->
  <Filth_Sand.label>areia</Filth_Sand.label>
  
  <!-- EN: scattered documents -->
  <Filth_ScatteredDocuments.label>documentos espalhados</Filth_ScatteredDocuments.label>
  
  <!-- EN: slime -->
  <Filth_Slime.label>limo</Filth_Slime.label>
  
  <!-- EN: spent acid -->
  <Filth_SpentAcid.label>ácido cuspido</Filth_SpentAcid.label>
  
  <!-- EN: trash -->
  <Filth_Trash.label>lixo</Filth_Trash.label>
  
  <!-- EN: vomit -->
  <Filth_Vomit.label>vômito</Filth_Vomit.label>
  
  <!-- EN: water puddle -->
  <Filth_Water.label>poça de água</Filth_Water.label>
  
  <!-- EN: scattered sandbags -->
  <SandbagRubble.label>sacos de areia espalhados</SandbagRubble.label>
  
  <!-- EN: scattered slag -->
  <SlagRubble.label>escória espalhada</SlagRubble.label>
  
</LanguageData>