<?xml version="1.0" encoding="utf-8"?>
<LanguageData>

  <TileSandstone.label>azulejo de arenito</TileSandstone.label>
  <TileSandstone.description>Azulejos de pedra refinadas e cuidadosamente cortadas para um sentimento de castelo. Bonito de se olhar, mas eles levam um longo tempo para serem colocados.</TileSandstone.description>

  <TileGranite.label>azulejo de granito</TileGranite.label>
  <TileGranite.description>Azulejos de pedra refinadas e cuidadosamente cortadas para um sentimento de castelo. Bonito de se olhar, mas eles levam um longo tempo para serem colocados.</TileGranite.description>

  <TileLimestone.label>azulejo de calcário</TileLimestone.label>
  <TileLimestone.description>Azulejos de pedra refinadas e cuidadosamente cortadas para um sentimento de castelo. Bonito de se olhar, mas eles levam um longo tempo para serem colocados.</TileLimestone.description>

  <TileSlate.label>azulejo de ardósia</TileSlate.label>
  <TileSlate.description>Azulejos de pedra refinadas e cuidadosamente cortadas para um sentimento de castelo. Bonito de se olhar, mas eles levam um longo tempo para serem colocados.</TileSlate.description>

  <TileMarble.label>azulejo de mármore</TileMarble.label>
  <TileMarble.description>Azulejos de pedra refinadas e cuidadosamente cortadas para um sentimento de castelo. Bonito de se olhar, mas eles levam um longo tempo para serem colocados.</TileMarble.description>

  <FlagstoneSandstone.label>laje de arenito</FlagstoneSandstone.label>
  <FlagstoneSandstone.description>Azulejos grosseiramente cortados de pedra. Não é super bonito, mas eles fazem boas superfícies para estradas e passarelas ao ar livre. Desconstruir essa laje não rende nenhum recurso.</FlagstoneSandstone.description>

  <FlagstoneGranite.label>laje de granito</FlagstoneGranite.label>
  <FlagstoneGranite.description>Azulejos grosseiramente cortados de pedra. Não é super bonito, mas eles fazem boas superfícies para estradas e passarelas ao ar livre. Desconstruir essa laje não rende nenhum recurso.</FlagstoneGranite.description>

  <FlagstoneLimestone.label>laje de calcário</FlagstoneLimestone.label>
  <FlagstoneLimestone.description>Azulejos grosseiramente cortados de pedra. Não é super bonito, mas eles fazem boas superfícies para estradas e passarelas ao ar livre. Desconstruir essa laje não rende nenhum recurso.</FlagstoneLimestone.description>

  <FlagstoneSlate.label>laje de ardósia</FlagstoneSlate.label>
  <FlagstoneSlate.description>Azulejos grosseiramente cortados de pedra. Não é super bonito, mas eles fazem boas superfícies para estradas e passarelas ao ar livre. Desconstruir essa laje não rende nenhum recurso.</FlagstoneSlate.description>

  <FlagstoneMarble.label>laje de mármore</FlagstoneMarble.label>
  <FlagstoneMarble.description>Azulejos grosseiramente cortados de pedra. Não é super bonito, mas eles fazem boas superfícies para estradas e passarelas ao ar livre. Desconstruir essa laje não rende nenhum recurso.</FlagstoneMarble.description>


</LanguageData>