<?xml version="1.0" encoding="UTF-8"?>
<LanguageData>
  
  <!-- EN: alphabeavers -->
  <Alphabeavers.label>alfacastores</Alphabeavers.label>
  
  <!-- EN: ambrosia sprout -->
  <AmbrosiaSprout.label>broto de ambrosia</AmbrosiaSprout.label>
  <!-- EN: Ambrosia sprout -->
  <AmbrosiaSprout.letterLabel>Broto de ambrosia</AmbrosiaSprout.letterLabel>
  <!-- EN: A grove of the mysterious ambrosia bush has sprouted nearby! If you wait for the plants to grow, you'll be able to harvest the delicious, pleasurable, and slightly addictive fruit. -->
  <AmbrosiaSprout.letterText>Alguns arbusto de ambrosia brotaram nas proximidades! Se você esperar que cresçam, poderá colher frutas deliciosas, prazerosas e ligeiramente viciantes.</AmbrosiaSprout.letterText>
  
  <!-- EN: cold snap -->
  <ColdSnap.label>onda de frio</ColdSnap.label>
  <!-- EN: Cold snap -->
  <ColdSnap.letterLabel>Onda de frio</ColdSnap.letterLabel>
  
  <!-- EN: crop blight -->
  <CropBlight.label>praga das plantações</CropBlight.label>
  
  <!-- EN: farm animals wander in -->
  <FarmAnimalsWanderIn.label>animais de fazenda se juntam</FarmAnimalsWanderIn.label>
  
  <!-- EN: flashstorm -->
  <Flashstorm.label>tempestade</Flashstorm.label>
  <!-- EN: Flashstorm -->
  <Flashstorm.letterLabel>Tempestade</Flashstorm.letterLabel>
  
  <!-- EN: heat wave -->
  <HeatWave.label>onda de calor</HeatWave.label>
  <!-- EN: Heat wave -->
  <HeatWave.letterLabel>Onda de calor</HeatWave.letterLabel>
  
  <!-- EN: herd migration -->
  <HerdMigration.label>migração de rebanho</HerdMigration.label>
  <!-- EN: Animal migration: {0} -->
  <HerdMigration.letterLabel>Migração de animais: {0}</HerdMigration.letterLabel>
  <!-- EN: A group of {0} is passing through the area.\n\nThey won't attack unless provoked. -->
  <HerdMigration.letterText>Um grupo de {0} está passando pela área.\n\nEles não atacarão a menos que sejam provocados.</HerdMigration.letterText>
  
  <!-- EN: meteorite impact -->
  <MeteoriteImpact.label>impacto de meteorito</MeteoriteImpact.label>
  <!-- EN: Meteorite -->
  <MeteoriteImpact.letterLabel>Meteorito</MeteoriteImpact.letterLabel>
  <!-- EN: A large meteorite has struck ground in the area. It has left behind a lump of {0}. -->
  <MeteoriteImpact.letterText>Um grande meteorito caiu na área. E deixou pedaços de {0}.</MeteoriteImpact.letterText>
  
  <!-- EN: psychic drone -->
  <PsychicDrone.label>zumbido psíquico</PsychicDrone.label>
  
  <!-- EN: psychic soothe -->
  <PsychicSoothe.label>calmante psíquico</PsychicSoothe.label>
  
  <!-- EN: ransom demand -->
  <RansomDemand.label>pedido de resgate</RansomDemand.label>
  <!-- EN: Ransom demand -->
  <RansomDemand.letterLabel>pedido de resgate</RansomDemand.letterLabel>
  
  <!-- EN: transport pod crash -->
  <RefugeePodCrash.label>colisão de cápsula de refugiado</RefugeePodCrash.label>
  
  <!-- EN: resource pod crash -->
  <ResourcePodCrash.label>colisão de cápsula de recursos</ResourcePodCrash.label>
  
  <!-- EN: self-tame -->
  <SelfTame.label>auto-domesticação</SelfTame.label>
  
  <!-- EN: short circuit -->
  <ShortCircuit.label>curto-circuito</ShortCircuit.label>
  
  <!-- EN: thrumbos pass -->
  <ThrumboPasses.label>passagem de trumbos</ThrumboPasses.label>
  
  <!-- EN: toxic fallout -->
  <ToxicFallout.label>precipitação tóxica</ToxicFallout.label>
  <!-- EN: Toxic fallout -->
  <ToxicFallout.letterLabel>Precipitação tóxica</ToxicFallout.letterLabel>
  
  <!-- EN: volcanic winter -->
  <VolcanicWinter.label>inverno vulcânico</VolcanicWinter.label>
  <!-- EN: Volcanic winter -->
  <VolcanicWinter.letterLabel>Inverno vulcânico</VolcanicWinter.letterLabel>
  
  <!-- EN: wanderer join -->
  <WandererJoin.label>aldeão se junta</WandererJoin.label>
  
  <!-- EN: wild man wanders in -->
  <WildManWandersIn.label>homem selvagem na área</WildManWandersIn.label>
  <!-- EN: {PAWN_kind} wanders in -->
  <WildManWandersIn.letterLabel>{PAWN_kind}</WildManWandersIn.letterLabel>
  <!-- EN: A person living among wild animals has wandered into the area. {PAWN_pronoun}'s called {0}.\n\nYou can attempt to tame or arrest {PAWN_objective}. -->
  <WildManWandersIn.letterText>Uma pessoa que vive entre animais selvagens entrou na área. {PAWN_pronoun} chama-se {0}.\n\nVocê pode tentar domar ou prender {PAWN_pronoun}.</WildManWandersIn.letterText>
  
</LanguageData>